Workbook

Sheet Cover
A1: TATA MOTORS — VALUATION & INVESTMENT STRATEGY | B1: TATA MOTORS — VALUATION & INVESTMENT STRATEGY | C1: TATA MOTORS — VALUATION & INVESTMENT STRATEGY | D1: TATA MOTORS — VALUATION & INVESTMENT STRATEGY | E1: TATA MOTORS — VALUATION & INVESTMENT STRATEGY | F1: TATA MOTORS — VALUATION & INVESTMENT STRATEGY | G1: TATA MOTORS — VALUATION & INVESTMENT STRATEGY | H1: TATA MOTORS — VALUATION & INVESTMENT STRATEGY
A2: FY2025-26 Commercial Vehicles business | Investment Banking Valuation Model
A4: Company | B4: Tata Motors Limited (Commercial Vehicles)
A5: Financial Year | B5: FY2025-26
A6: Valuation Date | B6: 7-Sep-2026 market benchmark / FY26A financial base
A7: Currency | B7: ₹ crore unless stated otherwise
A8: Primary Source | B8: Tata Motors 2nd Integrated Annual Report 2025-26
A10: MODEL SCOPE
A11: Standalone Tata Motors Commercial Vehicles valuation using (1) a 5-year DCF, (2) trading comparables, (3) precedent transaction cross-check, and (4) an investment strategy simulator. FY26A historical financials are sourced from the uploaded annual report. Peer trading multiples and the 7-Sep-2026 share-price benchmark are sourced from current market-data webpages.
A16: COLOR KEY
A17: Blue text / yellow fill | B17: Hardcoded input / user-editable assumption | D17: Important modeling note: the annual-report FY25 comparison is a 9-month period following the Company's demerger and is explicitly described as not comparable to FY26. The valuation therefore uses FY26A as the clean forecast base and treats transaction multiples as a cross-check rather than a primary weighting input.
A18: Green text | B18: Formula linked from another worksheet
A19: Black text | B19: Formula / calculation
A20: Red text | B20: External link / warning where applicable

Sheet Assumptions
A1: ASSUMPTIONS & MARKET INPUTS | B1: ASSUMPTIONS & MARKET INPUTS | C1: ASSUMPTIONS & MARKET INPUTS | D1: ASSUMPTIONS & MARKET INPUTS | E1: ASSUMPTIONS & MARKET INPUTS | F1: ASSUMPTIONS & MARKET INPUTS | G1: ASSUMPTIONS & MARKET INPUTS | H1: ASSUMPTIONS & MARKET INPUTS
A3: DCF Operating Assumptions | B3: DCF Operating Assumptions | C3: DCF Operating Assumptions | D3: DCF Operating Assumptions | F3: Valuation & Market Inputs | G3: Valuation & Market Inputs | H3: Valuation & Market Inputs
A4: Assumption | B4: Downside | C4: Base | D4: Upside | F4: Input | G4: Value | H4: Source / Note
A5: Revenue growth | B5: 0.04 | C5: 0.07 | D5: 0.09 | F5: Selected scenario | G5: Base | H5: User-editable
A6: EBITDA margin | B6: 0.115 | C6: 0.125 | D6: 0.13 | F6: WACC | G6: 0.11 | H6: Model assumption
A7: Tax rate | B7: 0.25 | C7: 0.25 | D7: 0.25 | F7: Terminal growth | G7: 0.04 | H7: Model assumption
A8: D&A / Revenue | B8: 0.023 | C8: 0.023 | D8: 0.023 | F8: Current share price | G8: 459.1 | H8: Business Standard, 7-Sep-2026
A9: Capex / Revenue | B9: 0.035 | C9: 0.035 | D9: 0.035 | F9: Equity shares outstanding (cr) | G9: 368 | H9: ₹736cr share capital / ₹2 face value
A10: NWC / Revenue | B10: 0.055 | C10: 0.055 | D10: 0.055 | F10: Current market capitalisation | G10: 169073 | H10: Business Standard, 7-Sep-2026 (source market cap)
F11: FY26A revenue | G11: ='Historical Financials'!C4 -> 83855 | H11: Linked from Historical Financials
F12: FY26A underlying EBITDA | G12: 10314 | H12: Tata Motors FY26 Annual Report p.214
A13: Selected Scenario Outputs | B13: Selected Scenario Outputs | C13: Selected Scenario Outputs | D13: Selected Scenario Outputs | F13: FY26A total debt | G13: 4817 | H13: Tata Motors FY26 Annual Report p.266 / MDA
A14: Selected | B14: Value
A15: Revenue growth | B15: =IF($G$5="Downside",$B$5,IF($G$5="Base",$C$5,$D$5)) -> 0.07
A16: EBITDA margin | B16: =IF($G$5="Downside",$B$6,IF($G$5="Base",$C$6,$D$6)) -> 0.125
A17: Tax rate | B17: =IF($G$5="Downside",$B$7,IF($G$5="Base",$C$7,$D$7)) -> 0.25
A18: D&A / Revenue | B18: =IF($G$5="Downside",$B$8,IF($G$5="Base",$C$8,$D$8)) -> 0.023
A19: Capex / Revenue | B19: =IF($G$5="Downside",$B$9,IF($G$5="Base",$C$9,$D$9)) -> 0.035
A20: NWC / Revenue | B20: =IF($G$5="Downside",$B$10,IF($G$5="Base",$C$10,$D$10)) -> 0.055

Sheet Historical Financials
A1: HISTORICAL FINANCIALS — FY2025-26 | B1: HISTORICAL FINANCIALS — FY2025-26 | C1: HISTORICAL FINANCIALS — FY2025-26 | D1: HISTORICAL FINANCIALS — FY2025-26 | E1: HISTORICAL FINANCIALS — FY2025-26 | F1: HISTORICAL FINANCIALS — FY2025-26
A3: Metric | B3: FY25 (9m) | C3: FY26A | D3: Source / Page | E3: Use | F3: Comment
A4: Revenue from operations | B4: 58217 | C4: 83855 | D4: Annual Report p.267 | E4: Base | F4: FY25 is 9m; not comparable
A5: Other income | B5: 877 | C5: 1124 | D5: Annual Report p.267 | E5: Context
A6: Total income | B6: 59094 | C6: 84979 | D6: Annual Report p.267 | E6: Context
A7: Cost of materials consumed | B7: 31167 | C7: 48840 | D7: Annual Report p.267 | E7: Driver
A8: Employee benefits expense | B8: 4223 | C8: 5804 | D8: Annual Report p.267 | E8: Driver
A9: Finance costs | B9: 1079 | C9: 874 | D9: Annual Report p.267 | E9: Bridge
A10: Depreciation & amortisation | B10: 1690 | C10: 1945 | D10: Annual Report p.267 | E10: DCF
A11: Product development / engineering | B11: 814 | C11: 789 | D11: Annual Report p.267 | E11: Context
A12: Other expenses | B12: 8672 | C12: 11689 | D12: Annual Report p.267 | E12: Driver
A13: FVTPL equity investment loss | B13: 0 | C13: 2418 | D13: Annual Report p.267 | E13: Exclude | F13: Non-operating / fair-value loss
A14: Profit before exceptional items & tax | B14: 4405 | C14: 6091 | D14: Annual Report p.267 | E14: Context
A15: Exceptional items | B15: 317 | C15: 1428 | D15: Annual Report p.267 | E15: Exclude
A16: Profit before tax | B16: 4088 | C16: 4663 | D16: Annual Report p.267 | E16: Context
A17: Tax expense | B17: 893 | C17: 1633 | D17: Annual Report p.267 | E17: Tax
A18: Profit after tax | B18: 3195 | C18: 3030 | D18: Annual Report p.267 | E18: Context
A19: Underlying EBITDA | B19: 6595 | C19: 10314 | D19: Annual Report p.214 | E19: DCF | F19: Underlying definition per MDA
A20: Underlying EBIT | B20: 5030 | C20: 8538 | D20: Annual Report p.214 | E20: DCF | F20: Underlying definition per MDA
A21: Operating cash flow | B21: 8547 | C21: 14981 | D21: Annual Report p.268 | E21: CF | F21: FY26
A22: Free cash flow | B22: 5880 | C22: 12438 | D22: Annual Report p.269 | E22: CF | F22: Company-defined auto FCF
A23: Total debt | B23: 9156 | C23: 4817 | D23: Annual Report pp.266/220 | E23: Bridge
A24: Cash & cash equivalents | B24: 1033 | C24: 6899 | D24: Annual Report p.266 | E24: Bridge
A25: Current investments | B25: 3036 | C25: 5274 | D25: Annual Report p.266 | E25: Bridge
A26: Short-term deposits | B26: 1195 | C26: 3593 | D26: Annual Report p.220 | E26: Bridge
A27: Total liquid assets | B27: 5264 | C27: 13048 | D27: Annual Report p.220 | E27: Bridge
A28: Total equity | B28: 10533 | C28: 12734 | D28: Annual Report p.266 | E28: Context
A29: Total assets | B29: 46851 | C29: 52309 | D29: Annual Report p.266 | E29: Context
A30: Inventories | B30: 4625 | C30: 5448 | D30: Annual Report p.266 | E30: NWC
A31: Trade receivables | B31: 3064 | C31: 2721 | D31: Annual Report p.266 | E31: NWC
A32: Trade payables | B32: 14376 | C32: 15704 | D32: Annual Report p.267 | E32: NWC
A34: Source note: the annual report states that the FY25 comparative P&L / cash flow covers only June 23, 2024 to March 31, 2025 and is not comparable with FY26.

Sheet DCF
A1: DISCOUNTED CASH FLOW — 5-YEAR DCF | B1: DISCOUNTED CASH FLOW — 5-YEAR DCF | C1: DISCOUNTED CASH FLOW — 5-YEAR DCF | D1: DISCOUNTED CASH FLOW — 5-YEAR DCF | E1: DISCOUNTED CASH FLOW — 5-YEAR DCF | F1: DISCOUNTED CASH FLOW — 5-YEAR DCF | G1: DISCOUNTED CASH FLOW — 5-YEAR DCF | H1: DISCOUNTED CASH FLOW — 5-YEAR DCF
A3: Metric | B3: FY26A | C3: FY27E | D3: FY28E | E3: FY29E | F3: FY30E | G3: FY31E | H3: Source / Formula
A4: Revenue | B4: ='Historical Financials'!C4 -> 83855 | C4: =B4*(1+Assumptions!$B$15) -> 89724.85 | D4: =C4*(1+Assumptions!$B$15) -> 96005.59 | E4: =D4*(1+Assumptions!$B$15) -> 102725.98 | F4: =E4*(1+Assumptions!$B$15) -> 109916.8 | G4: =F4*(1+Assumptions!$B$15) -> 117610.98 | H4: FY26A linked; future = prior year × (1 + growth)
A5: Growth | B5: =0 -> 0 | C5: =Assumptions!$B$15 -> 0.07 | D5: =Assumptions!$B$15 -> 0.07 | E5: =Assumptions!$B$15 -> 0.07 | F5: =Assumptions!$B$15 -> 0.07 | G5: =Assumptions!$B$15 -> 0.07 | H5: Assumption
A6: EBITDA | B6: ='Historical Financials'!C19 -> 10314 | C6: =C4*Assumptions!$B$16 -> 11215.606 | D6: =D4*Assumptions!$B$16 -> 12000.699 | E6: =E4*Assumptions!$B$16 -> 12840.748 | F6: =F4*Assumptions!$B$16 -> 13739.6 | G6: =G4*Assumptions!$B$16 -> 14701.372 | H6: Revenue × EBITDA margin
A7: EBITDA margin | B7: =B6/B4 -> 0.12299803 | C7: =Assumptions!$B$16 -> 0.125 | D7: =Assumptions!$B$16 -> 0.125 | E7: =Assumptions!$B$16 -> 0.125 | F7: =Assumptions!$B$16 -> 0.125 | G7: =Assumptions!$B$16 -> 0.125 | H7: Assumption
A8: D&A | B8: ='Historical Financials'!C10 -> 1945 | C8: =C4*Assumptions!$B$18 -> 2063.6716 | D8: =D4*Assumptions!$B$18 -> 2208.1286 | E8: =E4*Assumptions!$B$18 -> 2362.6976 | F8: =F4*Assumptions!$B$18 -> 2528.0864 | G8: =G4*Assumptions!$B$18 -> 2705.0524 | H8: Revenue × D&A / Revenue
A9: EBIT | B9: =B6-B8 -> 8369 | C9: =C6-C8 -> 9151.9347 | D9: =D6-D8 -> 9792.5701 | E9: =E6-E8 -> 10478.05 | F9: =F6-F8 -> 11211.514 | G9: =G6-G8 -> 11996.319 | H9: EBITDA − D&A
A10: Tax on EBIT | B10: =B9*Assumptions!$B$17 -> 2092.25 | C10: =C9*Assumptions!$B$17 -> 2287.9837 | D10: =D9*Assumptions!$B$17 -> 2448.1425 | E10: =E9*Assumptions!$B$17 -> 2619.5125 | F10: =F9*Assumptions!$B$17 -> 2802.8784 | G10: =G9*Assumptions!$B$17 -> 2999.0799 | H10: EBIT × tax rate
A11: NOPAT | B11: =B9-B10 -> 6276.75 | C11: =C9-C10 -> 6863.951 | D11: =D9-D10 -> 7344.4276 | E11: =E9-E10 -> 7858.5375 | F11: =F9-F10 -> 8408.6352 | G11: =G9-G10 -> 8997.2396 | H11: EBIT − tax on EBIT
A12: Capex | B12: =B4*Assumptions!$B$19 -> 2934.925 | C12: =C4*Assumptions!$B$19 -> 3140.3698 | D12: =D4*Assumptions!$B$19 -> 3360.1956 | E12: =E4*Assumptions!$B$19 -> 3595.4093 | F12: =F4*Assumptions!$B$19 -> 3847.088 | G12: =G4*Assumptions!$B$19 -> 4116.3841 | H12: Revenue × capex / revenue
A13: NWC | B13: =B4*Assumptions!$B$20 -> 4612.025 | C13: =C4*Assumptions!$B$20 -> 4934.8668 | D13: =D4*Assumptions!$B$20 -> 5280.3074 | E13: =E4*Assumptions!$B$20 -> 5649.9289 | F13: =F4*Assumptions!$B$20 -> 6045.424 | G13: =G4*Assumptions!$B$20 -> 6468.6036 | H13: Revenue × NWC / Revenue
A14: Change in NWC | B14: =0 -> 0 | C14: =C13-B13 -> 322.84175 | D14: =D13-C13 -> 345.44067 | E14: =E13-D13 -> 369.62152 | F14: =F13-E13 -> 395.49503 | G14: =G13-F13 -> 423.17968 | H14: Current NWC − prior year NWC
A15: Unlevered FCF | B15: =B11+B8-B12-B14 -> 5286.825 | C15: =C11+C8-C12-C14 -> 5464.4111 | D15: =D11+D8-D12-D14 -> 5846.9199 | E15: =E11+E8-E12-E14 -> 6256.2042 | F15: =F11+F8-F12-F14 -> 6694.1385 | G15: =G11+G8-G12-G14 -> 7162.7282 | H15: NOPAT + D&A − Capex − Change in NWC
A16: Discount factor | B16: =1 -> 1 | C16: =1/(1+Assumptions!$G$6)^(COLUMN()-2) -> 0.9009009 | D16: =1/(1+Assumptions!$G$6)^(COLUMN()-2) -> 0.81162243 | E16: =1/(1+Assumptions!$G$6)^(COLUMN()-2) -> 0.73119138 | F16: =1/(1+Assumptions!$G$6)^(COLUMN()-2) -> 0.65873097 | G16: =1/(1+Assumptions!$G$6)^(COLUMN()-2) -> 0.59345133 | H16: 1 / (1 + WACC)^t
A17: PV of FCF | B17: =B15*B16 -> 5286.825 | C17: =C15*C16 -> 4922.8929 | D17: =D15*D16 -> 4745.4913 | E17: =E15*E16 -> 4574.4826 | F17: =F15*F16 -> 4409.6364 | G17: =G15*G16 -> 4250.7306 | H17: FCF × discount factor
A20: DCF VALUATION BRIDGE | B20: DCF VALUATION BRIDGE | C20: DCF VALUATION BRIDGE | D20: DCF VALUATION BRIDGE
A21: Metric | B21: Value | C21: Unit | D21: Formula / Note
A22: PV of explicit FCF | B22: =SUM(C17:G17) -> 22903.234 | C22: ₹ cr | D22: SUM(PV of FCF)
A23: Terminal year FCF | B23: =G15 -> 7162.7282 | C23: ₹ cr | D23: FY31E Unlevered FCF
A24: Terminal growth | B24: =Assumptions!$G$7 -> 0.04 | C24: % | D24: Assumption
A25: Terminal value | B25: =B23*(1+B24)/(Assumptions!$G$6-B24) -> 106417.68 | C25: ₹ cr | D25: FY31 FCF × (1+g)/(WACC−g)
A26: PV of terminal value | B26: =B25/(1+Assumptions!$G$6)^5 -> 63153.712 | C26: ₹ cr | D26: TV / (1+WACC)^5
A27: Enterprise value | B27: =SUM(B22,B26) -> 86056.945 | C27: ₹ cr | D27: Explicit PV + PV of TV
A28: Net cash adjustment | B28: ='Historical Financials'!C24-'Historical Financials'!C23 -> 2082 | C28: ₹ cr | D28: Cash & equivalents − debt
A29: Implied equity value | B29: =SUM(B27,B28) -> 88138.945 | C29: ₹ cr | D29: EV + net cash
A31: Key Output | B31: Value | C31: Unit | D31: Interpretation
A32: Implied share value | B32: =B29/Assumptions!$G$9 -> 239.508 | C32: ₹ / share | D32: DCF equity value / 368cr shares
A33: Current market price | B33: =Assumptions!$G$8 -> 459.1 | C33: ₹ / share | D33: 7-Sep-2026 benchmark
A34: Upside / (downside) | B34: =B32/B33-1 -> -0.47830973 | C34: % | D34: (DCF value / current price) − 1
A37: WACC / Terminal Growth Sensitivity | B37: 0.03 | C37: 0.035 | D37: 0.04 | E37: 0.045 | F37: 0.05
A38: 0.1 | B38: =($B$22+($B$23*(1+B$37)/($A38-B$37))/((1+$A38)^5)+$B$28)/Assumptions!$G$9 -> 245.72522 | C38: =($B$22+($B$23*(1+C$37)/($A38-C$37))/((1+$A38)^5)+$B$28)/Assumptions!$G$9 -> 260.33416 | D38: =($B$22+($B$23*(1+D$37)/($A38-D$37))/((1+$A38)^5)+$B$28)/Assumptions!$G$9 -> 277.37791 | E38: =($B$22+($B$23*(1+E$37)/($A38-E$37))/((1+$A38)^5)+$B$28)/Assumptions!$G$9 -> 297.52054 | F38: =($B$22+($B$23*(1+F$37)/($A38-F$37))/((1+$A38)^5)+$B$28)/Assumptions!$G$9 -> 321.69168
A39: 0.105 | B39: =($B$22+($B$23*(1+B$37)/($A39-B$37))/((1+$A39)^5)+$B$28)/Assumptions!$G$9 -> 230.14859 | C39: =($B$22+($B$23*(1+C$37)/($A39-C$37))/((1+$A39)^5)+$B$28)/Assumptions!$G$9 -> 242.58205 | D39: =($B$22+($B$23*(1+D$37)/($A39-D$37))/((1+$A39)^5)+$B$28)/Assumptions!$G$9 -> 256.92836 | E39: =($B$22+($B$23*(1+E$37)/($A39-E$37))/((1+$A39)^5)+$B$28)/Assumptions!$G$9 -> 273.66572 | F39: =($B$22+($B$23*(1+F$37)/($A39-F$37))/((1+$A39)^5)+$B$28)/Assumptions!$G$9 -> 293.44624
A40: 0.11 | B40: =($B$22+($B$23*(1+B$37)/($A40-B$37))/((1+$A40)^5)+$B$28)/Assumptions!$G$9 -> 216.61247 | C40: =($B$22+($B$23*(1+C$37)/($A40-C$37))/((1+$A40)^5)+$B$28)/Assumptions!$G$9 -> 227.29705 | D40: =($B$22+($B$23*(1+D$37)/($A40-D$37))/((1+$A40)^5)+$B$28)/Assumptions!$G$9 -> 239.508 | E40: =($B$22+($B$23*(1+E$37)/($A40-E$37))/((1+$A40)^5)+$B$28)/Assumptions!$G$9 -> 253.59756 | F40: =($B$22+($B$23*(1+F$37)/($A40-F$37))/((1+$A40)^5)+$B$28)/Assumptions!$G$9 -> 270.03538
A41: 0.115 | B41: =($B$22+($B$23*(1+B$37)/($A41-B$37))/((1+$A41)^5)+$B$28)/Assumptions!$G$9 -> 204.75405 | C41: =($B$22+($B$23*(1+C$37)/($A41-C$37))/((1+$A41)^5)+$B$28)/Assumptions!$G$9 -> 214.01365 | D41: =($B$22+($B$23*(1+D$37)/($A41-D$37))/((1+$A41)^5)+$B$28)/Assumptions!$G$9 -> 224.50787 | E41: =($B$22+($B$23*(1+E$37)/($A41-E$37))/((1+$A41)^5)+$B$28)/Assumptions!$G$9 -> 236.50126 | F41: =($B$22+($B$23*(1+F$37)/($A41-F$37))/((1+$A41)^5)+$B$28)/Assumptions!$G$9 -> 250.33978
A42: 0.12 | B42: =($B$22+($B$23*(1+B$37)/($A42-B$37))/((1+$A42)^5)+$B$28)/Assumptions!$G$9 -> 194.29122 | C42: =($B$22+($B$23*(1+C$37)/($A42-C$37))/((1+$A42)^5)+$B$28)/Assumptions!$G$9 -> 202.37598 | D42: =($B$22+($B$23*(1+D$37)/($A42-D$37))/((1+$A42)^5)+$B$28)/Assumptions!$G$9 -> 211.47133 | E42: =($B$22+($B$23*(1+E$37)/($A42-E$37))/((1+$A42)^5)+$B$28)/Assumptions!$G$9 -> 221.7794 | F42: =($B$22+($B$23*(1+F$37)/($A42-F$37))/((1+$A42)^5)+$B$28)/Assumptions!$G$9 -> 233.56005
A45: FCF VISUAL | B45: FCF VISUAL | C45: FCF VISUAL | D45: FCF VISUAL | E45: FCF VISUAL | F45: FCF VISUAL | G45: FCF VISUAL
A46: Year | B46: FY26A | C46: FY27E | D46: FY28E | E46: FY29E | F46: FY30E | G46: FY31E
A47: Unlevered FCF | B47: =B15 -> 5286.825 | C47: =C15 -> 5464.4111 | D47: =D15 -> 5846.9199 | E47: =E15 -> 6256.2042 | F47: =F15 -> 6694.1385 | G47: =G15 -> 7162.7282

Sheet Trading Comps
A1: TRADING COMPARABLES — FY2026 | B1: TRADING COMPARABLES — FY2026 | C1: TRADING COMPARABLES — FY2026 | D1: TRADING COMPARABLES — FY2026 | E1: TRADING COMPARABLES — FY2026 | F1: TRADING COMPARABLES — FY2026 | G1: TRADING COMPARABLES — FY2026 | H1: TRADING COMPARABLES — FY2026 | I1: TRADING COMPARABLES — FY2026
A3: Company | B3: Ticker | C3: FY26 EV / Sales | D3: FY26 EV / EBITDA | E3: Selected | F3: Comment | G3: Source | H3: Tata Revenue Applied | I3: Tata EBITDA Applied
A4: Ashok Leyland | B4: ASHOKLEY | C4: 2.48 | D4: 11.6 | E4: Yes | F4: Pure-play Indian CV with financing business | G4: StockAnalysis | H4: ='Historical Financials'!C4 -> 83855 | I4: ='Historical Financials'!C19 -> 10314
A5: Force Motors | B5: FORCEMOT | C5: 2.77 | D5: 16.78 | E5: Yes | F5: Indian CV / light commercial vehicle exposure | G5: StockAnalysis | H5: ='Historical Financials'!C4 -> 83855 | I5: ='Historical Financials'!C19 -> 10314
A6: Eicher Motors | B6: EICHERMOT | C6: 7.57 | D6: 32.4 | E6: No | F6: Diversified; Royal Enfield makes it a higher-multiple cross-check | G6: StockAnalysis | H6: ='Historical Financials'!C4 -> 83855 | I6: ='Historical Financials'!C19 -> 10314
A9: Selected Peer Set — Ashok Leyland + Force Motors | B9: Selected Peer Set — Ashok Leyland + Force Motors | C9: Selected Peer Set — Ashok Leyland + Force Motors | D9: Selected Peer Set — Ashok Leyland + Force Motors | E9: Selected Peer Set — Ashok Leyland + Force Motors | F9: Selected Peer Set — Ashok Leyland + Force Motors
A10: Metric | B10: Ashok Leyland | C10: Force Motors | D10: Selected Average | E10: Tata Implied EV | F10: Tata Implied Equity
A11: EV / Sales | B11: 2.48 | C11: 2.77 | D11: =AVERAGE(B11:C11) -> 2.625 | E11: =D11*'Historical Financials'!C4 -> 220119.38 | F11: =SUM(E11,D13) -> 222201.38
A12: EV / EBITDA | B12: 11.6 | C12: 16.78 | D12: =AVERAGE(B12:C12) -> 14.19 | E12: =D12*'Historical Financials'!C19 -> 146355.66 | F12: =SUM(E12,D13) -> 148437.66
A13: Net cash adjustment | D13: ='Historical Financials'!C24-'Historical Financials'!C23 -> 2082
A14: Implied share value (EV / Sales) | F14: =F11/Assumptions!$G$9 -> 603.80808
A15: Implied share value (EV / EBITDA) | F15: =F12/Assumptions!$G$9 -> 403.36321
A18: Selected Trading Value | B18: Selected Trading Value | C18: Selected Trading Value | D18: Selected Trading Value | E18: Selected Trading Value
A19: Method | B19: Implied Equity Value | C19: Implied Share Value | D19: Weight | E19: Weighted Share Value
A20: EV / Sales | B20: =F11 -> 222201.38 | C20: =B20/Assumptions!$G$9 -> 603.80808 | D20: 0.5 | E20: =C20*D20 -> 301.90404
A21: EV / EBITDA | B21: =F12 -> 148437.66 | C21: =B21/Assumptions!$G$9 -> 403.36321 | D21: 0.5 | E21: =C21*D21 -> 201.6816
A22: Trading Comps Selected Value | B22: =SUM(B20:B21) -> 370639.04 | C22: =SUM(E20:E21) -> 503.58565 | D22: =SUM(D20:D21) -> 1
A24: Peer-set note: Eicher Motors is shown as a market reference but excluded from the selected median/average because it is materially diversified beyond commercial vehicles.
A27: Company | B27: EV / Sales | C27: EV / EBITDA | D27: Selected
A28: Ashok Leyland | B28: 2.48 | C28: 11.6 | D28: Yes
A29: Force Motors | B29: 2.77 | C29: 16.78 | D29: Yes
A30: Eicher Motors | B30: 7.57 | C30: 32.4 | D30: No

Sheet Precedent Transactions
A1: PRECEDENT TRANSACTIONS — IVECO CROSS-CHECK | B1: PRECEDENT TRANSACTIONS — IVECO CROSS-CHECK | C1: PRECEDENT TRANSACTIONS — IVECO CROSS-CHECK | D1: PRECEDENT TRANSACTIONS — IVECO CROSS-CHECK | E1: PRECEDENT TRANSACTIONS — IVECO CROSS-CHECK | F1: PRECEDENT TRANSACTIONS — IVECO CROSS-CHECK | G1: PRECEDENT TRANSACTIONS — IVECO CROSS-CHECK | H1: PRECEDENT TRANSACTIONS — IVECO CROSS-CHECK
A3: Transaction | B3: Buyer | C3: Target | D3: Equity Consideration | E3: Target Revenue | F3: P / Sales | G3: Use | H3: Source
A4: Proposed IVECO acquisition | B4: Tata Motors | C4: IVECO Group | D4: 3.8 | E4: 13.4 | F4: =D4/E4 -> 0.28358209 | G4: Cross-check only — transaction structure / target mix differs from Tata CV | H4: Annual Report FY26 p.117 / Chairman's Message
A7: Transaction Bridge | B7: Transaction Bridge | C7: Transaction Bridge | D7: Transaction Bridge
A8: Metric | B8: Value | C8: Unit | D8: Comment
A9: Purchase price | B9: 3.8 | C9: €bn | D9: Annual report transaction evidence
A10: Target revenue | B10: 13.4 | C10: €bn | D10: 2025 revenue cited by Tata Motors
A11: Purchase price / sales | B11: =B9/B10 -> 0.28358209 | C11: x | D11: Derived
A12: INR purchase consideration | B12: 41691 | C12: ₹ cr | D12: Annual report transaction evidence
A13: INR / EUR translation (check) | B13: =B12/B9 -> 10971.316 | C13: ₹/€ | D13: Implied from reported consideration / €3.8bn
A14: Applied to Tata FY26 revenue | B14: =B11*'Historical Financials'!C4 -> 23779.776 | C14: ₹ cr | D14: Illustrative only — not used in selected target
A16: Interpretation: the IVECO transaction supplies a real-world purchase-price benchmark, but it is not a clean trading-multiple anchor for Tata Motors. The source reports the transaction as an equity consideration and the target business mix/transaction perimeter differs. Accordingly, this analysis is deliberately presented as a cross-check and is excluded from the selected valuation weighting.

Sheet Investment Simulation
A1: INVESTMENT STRATEGY SIMULATION | B1: INVESTMENT STRATEGY SIMULATION | C1: INVESTMENT STRATEGY SIMULATION | D1: INVESTMENT STRATEGY SIMULATION | E1: INVESTMENT STRATEGY SIMULATION | F1: INVESTMENT STRATEGY SIMULATION | G1: INVESTMENT STRATEGY SIMULATION | H1: INVESTMENT STRATEGY SIMULATION
A3: Scenario Return Analysis | B3: Scenario Return Analysis | C3: Scenario Return Analysis | D3: Scenario Return Analysis
A4: Scenario | B4: DCF Share Value | C4: Trading Comps Share Value | D4: Weighted Target
A5: Downside | B5: =((((((('Historical Financials'!$C$4*(1+Assumptions!$B$5)^1)*Assumptions!$B$6-('Historical Financials'!$C$4*(1+Assumptions!$B$5)^1)*Assumptions!$B$8)*(1-Assumptions!$B$7))+('Historical Financials'!$C$4*(1+Assumptions!$B$5)^1)*Assumptions!$B$8-(('Historical Financials'!$C$4*(1+Assumptions!$B$5)^1)*Assumptions!$B$9)-((('Historical Financials'!$C$4*(1+Assumptions!$B$5)^1)*Assumptions!$B$10)-(('Historical Financials'!$C$4*(1+Assumptions!$B$5)^0)*Assumptions!$B$10)))/(1+Assumptions!$G$6)^1) + ((((('Historical Financials'!$C$4*(1+Assumptions!$B$5)^2)*Assumptions!$B$6-('Historical Financials'!$C$4*(1+Assumptions!$B$5)^2)*Assumptions!$B$8)*(1-Assumptions!$B$7))+('Historical Financials'!$C$4*(1+Assumptions!$B$5)^2)*Assumptions!$B$8-(('Historical Financials'!$C$4*(1+Assumptions!$B$5)^2)*Assumptions!$B$9)-((('Historical Financials'!$C$4*(1+Assumptions!$B$5)^2)*Assumptions!$B$10)-(('Historical Financials'!$C$4*(1+Assumptions!$B$5)^1)*Assumptions!$B$10)))/(1+Assumptions!$G$6)^2) + ((((('Historical Financials'!$C$4*(1+Assumptions!$B$5)^3)*Assumptions!$B$6-('Historical Financials'!$C$4*(1+Assumptions!$B$5)^3)*Assumptions!$B$8)*(1-Assumptions!$B$7))+('Historical Financials'!$C$4*(1+Assumptions!$B$5)^3)*Assumptions!$B$8-(('Historical Financials'!$C$4*(1+Assumptions!$B$5)^3)*Assumptions!$B$9)-((('Historical Financials'!$C$4*(1+Assumptions!$B$5)^3)*Assumptions!$B$10)-(('Historical Financials'!$C$4*(1+Assumptions!$B$5)^2)*Assumptions!$B$10)))/(1+Assumptions!$G$6)^3) + ((((('Historical Financials'!$C$4*(1+Assumptions!$B$5)^4)*Assumptions!$B$6-('Historical Financials'!$C$4*(1+Assumptions!$B$5)^4)*Assumptions!$B$8)*(1-Assumptions!$B$7))+('Historical Financials'!$C$4*(1+Assumptions!$B$5)^4)*Assumptions!$B$8-(('Historical Financials'!$C$4*(1+Assumptions!$B$5)^4)*Assumptions!$B$9)-((('Historical Financials'!$C$4*(1+Assumptions!$B$5)^4)*Assumptions!$B$10)-(('Historical Financials'!$C$4*(1+Assumptions!$B$5)^3)*Assumptions!$B$10)))/(1+Assumptions!$G$6)^4) + ((((('Historical Financials'!$C$4*(1+Assumptions!$B$5)^5)*Assumptions!$B$6-('Historical Financials'!$C$4*(1+Assumptions!$B$5)^5)*Assumptions!$B$8)*(1-Assumptions!$B$7))+('Historical Financials'!$C$4*(1+Assumptions!$B$5)^5)*Assumptions!$B$8-(('Historical Financials'!$C$4*(1+Assumptions!$B$5)^5)*Assumptions!$B$9)-((('Historical Financials'!$C$4*(1+Assumptions!$B$5)^5)*Assumptions!$B$10)-(('Historical Financials'!$C$4*(1+Assumptions!$B$5)^4)*Assumptions!$B$10)))/(1+Assumptions!$G$6)^5))+(((((('Historical Financials'!$C$4*(1+Assumptions!$B$5)^5)*Assumptions!$B$6-('Historical Financials'!$C$4*(1+Assumptions!$B$5)^5)*Assumptions!$B$8)*(1-Assumptions!$B$7))+('Historical Financials'!$C$4*(1+Assumptions!$B$5)^5)*Assumptions!$B$8-(('Historical Financials'!$C$4*(1+Assumptions!$B$5)^5)*Assumptions!$B$9)-((('Historical Financials'!$C$4*(1+Assumptions!$B$5)^5)*Assumptions!$B$10)-('Historical Financials'!$C$4*(1+Assumptions!$B$5)^4*Assumptions!$B$10))))*(1+Assumptions!$G$7)/(Assumptions!$G$6-Assumptions!$G$7))/((1+Assumptions!$G$6)^5)+('Historical Financials'!$C$24-'Historical Financials'!$C$23))/Assumptions!$G$9 -> 191.46675 | C5: ='Trading Comps'!$C$22 -> 503.58565 | D5: =AVERAGE(B5,C5) -> 347.5262
A6: Base | B6: =((((((('Historical Financials'!$C$4*(1+Assumptions!$C$5)^1)*Assumptions!$C$6-('Historical Financials'!$C$4*(1+Assumptions!$C$5)^1)*Assumptions!$B$8)*(1-Assumptions!$C$7))+('Historical Financials'!$C$4*(1+Assumptions!$C$5)^1)*Assumptions!$B$8-(('Historical Financials'!$C$4*(1+Assumptions!$C$5)^1)*Assumptions!$C$9)-((('Historical Financials'!$C$4*(1+Assumptions!$C$5)^1)*Assumptions!$C$10)-(('Historical Financials'!$C$4*(1+Assumptions!$C$5)^0)*Assumptions!$C$10)))/(1+Assumptions!$G$6)^1) + ((((('Historical Financials'!$C$4*(1+Assumptions!$C$5)^2)*Assumptions!$C$6-('Historical Financials'!$C$4*(1+Assumptions!$C$5)^2)*Assumptions!$B$8)*(1-Assumptions!$C$7))+('Historical Financials'!$C$4*(1+Assumptions!$C$5)^2)*Assumptions!$B$8-(('Historical Financials'!$C$4*(1+Assumptions!$C$5)^2)*Assumptions!$C$9)-((('Historical Financials'!$C$4*(1+Assumptions!$C$5)^2)*Assumptions!$C$10)-(('Historical Financials'!$C$4*(1+Assumptions!$C$5)^1)*Assumptions!$C$10)))/(1+Assumptions!$G$6)^2) + ((((('Historical Financials'!$C$4*(1+Assumptions!$C$5)^3)*Assumptions!$C$6-('Historical Financials'!$C$4*(1+Assumptions!$C$5)^3)*Assumptions!$B$8)*(1-Assumptions!$C$7))+('Historical Financials'!$C$4*(1+Assumptions!$C$5)^3)*Assumptions!$B$8-(('Historical Financials'!$C$4*(1+Assumptions!$C$5)^3)*Assumptions!$C$9)-((('Historical Financials'!$C$4*(1+Assumptions!$C$5)^3)*Assumptions!$C$10)-(('Historical Financials'!$C$4*(1+Assumptions!$C$5)^2)*Assumptions!$C$10)))/(1+Assumptions!$G$6)^3) + ((((('Historical Financials'!$C$4*(1+Assumptions!$C$5)^4)*Assumptions!$C$6-('Historical Financials'!$C$4*(1+Assumptions!$C$5)^4)*Assumptions!$B$8)*(1-Assumptions!$C$7))+('Historical Financials'!$C$4*(1+Assumptions!$C$5)^4)*Assumptions!$B$8-(('Historical Financials'!$C$4*(1+Assumptions!$C$5)^4)*Assumptions!$C$9)-((('Historical Financials'!$C$4*(1+Assumptions!$C$5)^4)*Assumptions!$C$10)-(('Historical Financials'!$C$4*(1+Assumptions!$C$5)^3)*Assumptions!$C$10)))/(1+Assumptions!$G$6)^4) + ((((('Historical Financials'!$C$4*(1+Assumptions!$C$5)^5)*Assumptions!$C$6-('Historical Financials'!$C$4*(1+Assumptions!$C$5)^5)*Assumptions!$B$8)*(1-Assumptions!$C$7))+('Historical Financials'!$C$4*(1+Assumptions!$C$5)^5)*Assumptions!$B$8-(('Historical Financials'!$C$4*(1+Assumptions!$C$5)^5)*Assumptions!$C$9)-((('Historical Financials'!$C$4*(1+Assumptions!$C$5)^5)*Assumptions!$C$10)-(('Historical Financials'!$C$4*(1+Assumptions!$C$5)^4)*Assumptions!$C$10)))/(1+Assumptions!$G$6)^5))+(((((('Historical Financials'!$C$4*(1+Assumptions!$C$5)^5)*Assumptions!$C$6-('Historical Financials'!$C$4*(1+Assumptions!$C$5)^5)*Assumptions!$B$8)*(1-Assumptions!$C$7))+('Historical Financials'!$C$4*(1+Assumptions!$C$5)^5)*Assumptions!$B$8-(('Historical Financials'!$C$4*(1+Assumptions!$C$5)^5)*Assumptions!$C$9)-((('Historical Financials'!$C$4*(1+Assumptions!$C$5)^5)*Assumptions!$C$10)-('Historical Financials'!$C$4*(1+Assumptions!$C$5)^4*Assumptions!$C$10))))*(1+Assumptions!$G$7)/(Assumptions!$G$6-Assumptions!$G$7))/((1+Assumptions!$G$6)^5)+('Historical Financials'!$C$24-'Historical Financials'!$C$23))/Assumptions!$G$9 -> 239.508 | C6: ='Trading Comps'!$C$22 -> 503.58565 | D6: =AVERAGE(B6,C6) -> 371.54682
A7: Upside | B7: =((((((('Historical Financials'!$C$4*(1+Assumptions!$D$5)^1)*Assumptions!$D$6-('Historical Financials'!$C$4*(1+Assumptions!$D$5)^1)*Assumptions!$B$8)*(1-Assumptions!$D$7))+('Historical Financials'!$C$4*(1+Assumptions!$D$5)^1)*Assumptions!$B$8-(('Historical Financials'!$C$4*(1+Assumptions!$D$5)^1)*Assumptions!$D$9)-((('Historical Financials'!$C$4*(1+Assumptions!$D$5)^1)*Assumptions!$D$10)-(('Historical Financials'!$C$4*(1+Assumptions!$D$5)^0)*Assumptions!$D$10)))/(1+Assumptions!$G$6)^1) + ((((('Historical Financials'!$C$4*(1+Assumptions!$D$5)^2)*Assumptions!$D$6-('Historical Financials'!$C$4*(1+Assumptions!$D$5)^2)*Assumptions!$B$8)*(1-Assumptions!$D$7))+('Historical Financials'!$C$4*(1+Assumptions!$D$5)^2)*Assumptions!$B$8-(('Historical Financials'!$C$4*(1+Assumptions!$D$5)^2)*Assumptions!$D$9)-((('Historical Financials'!$C$4*(1+Assumptions!$D$5)^2)*Assumptions!$D$10)-(('Historical Financials'!$C$4*(1+Assumptions!$D$5)^1)*Assumptions!$D$10)))/(1+Assumptions!$G$6)^2) + ((((('Historical Financials'!$C$4*(1+Assumptions!$D$5)^3)*Assumptions!$D$6-('Historical Financials'!$C$4*(1+Assumptions!$D$5)^3)*Assumptions!$B$8)*(1-Assumptions!$D$7))+('Historical Financials'!$C$4*(1+Assumptions!$D$5)^3)*Assumptions!$B$8-(('Historical Financials'!$C$4*(1+Assumptions!$D$5)^3)*Assumptions!$D$9)-((('Historical Financials'!$C$4*(1+Assumptions!$D$5)^3)*Assumptions!$D$10)-(('Historical Financials'!$C$4*(1+Assumptions!$D$5)^2)*Assumptions!$D$10)))/(1+Assumptions!$G$6)^3) + ((((('Historical Financials'!$C$4*(1+Assumptions!$D$5)^4)*Assumptions!$D$6-('Historical Financials'!$C$4*(1+Assumptions!$D$5)^4)*Assumptions!$B$8)*(1-Assumptions!$D$7))+('Historical Financials'!$C$4*(1+Assumptions!$D$5)^4)*Assumptions!$B$8-(('Historical Financials'!$C$4*(1+Assumptions!$D$5)^4)*Assumptions!$D$9)-((('Historical Financials'!$C$4*(1+Assumptions!$D$5)^4)*Assumptions!$D$10)-(('Historical Financials'!$C$4*(1+Assumptions!$D$5)^3)*Assumptions!$D$10)))/(1+Assumptions!$G$6)^4) + ((((('Historical Financials'!$C$4*(1+Assumptions!$D$5)^5)*Assumptions!$D$6-('Historical Financials'!$C$4*(1+Assumptions!$D$5)^5)*Assumptions!$B$8)*(1-Assumptions!$D$7))+('Historical Financials'!$C$4*(1+Assumptions!$D$5)^5)*Assumptions!$B$8-(('Historical Financials'!$C$4*(1+Assumptions!$D$5)^5)*Assumptions!$D$9)-((('Historical Financials'!$C$4*(1+Assumptions!$D$5)^5)*Assumptions!$D$10)-(('Historical Financials'!$C$4*(1+Assumptions!$D$5)^4)*Assumptions!$D$10)))/(1+Assumptions!$G$6)^5))+(((((('Historical Financials'!$C$4*(1+Assumptions!$D$5)^5)*Assumptions!$D$6-('Historical Financials'!$C$4*(1+Assumptions!$D$5)^5)*Assumptions!$B$8)*(1-Assumptions!$D$7))+('Historical Financials'!$C$4*(1+Assumptions!$D$5)^5)*Assumptions!$B$8-(('Historical Financials'!$C$4*(1+Assumptions!$D$5)^5)*Assumptions!$D$9)-((('Historical Financials'!$C$4*(1+Assumptions!$D$5)^5)*Assumptions!$D$10)-('Historical Financials'!$C$4*(1+Assumptions!$D$5)^4*Assumptions!$D$10))))*(1+Assumptions!$G$7)/(Assumptions!$G$6-Assumptions!$G$7))/((1+Assumptions!$G$6)^5)+('Historical Financials'!$C$24-'Historical Financials'!$C$23))/Assumptions!$G$9 -> 271.35211 | C7: ='Trading Comps'!$C$22 -> 503.58565 | D7: =AVERAGE(B7,C7) -> 387.46888
A8: Current price | B8: =Assumptions!$G$8 -> 459.1 | C8: ='Trading Comps'!$C$22 -> 503.58565 | D8: =Assumptions!$G$8 -> 459.1
A11: Base-Case Position Simulator | B11: Base-Case Position Simulator | C11: Base-Case Position Simulator | D11: Base-Case Position Simulator | E11: Base-Case Position Simulator | F11: Base-Case Position Simulator
A12: Input / Output | B12: Value | C12: Unit | D12: Formula | E12: Editable? | F12: Note
A13: Investment amount | B13: 100000 | C13: ₹ | D13: User input | E13: Yes | F13: Example only
A14: Entry price | B14: =Assumptions!$G$8 -> 459.1 | C14: ₹ / share | D14: Current market price | E14: No | F14: 7-Sep-2026
A15: Shares purchased | B15: =B13/B14 -> 217.81747 | C15: shares | D15: Investment / entry price | E15: No | F15: Fractional shares shown
A16: Base target price | B16: =D6 -> 371.54682 | C16: ₹ / share | D16: Base weighted target | E16: No | F16: 50% DCF + 50% comps
A17: Target value | B17: =B15*B16 -> 80929.389 | C17: ₹ | D17: Shares × target | E17: No
A18: Profit / (loss) | B18: =B17-B13 -> -19070.611 | C18: ₹ | D18: Target value − investment | E18: No
A19: Return | B19: =B18/B13 -> -0.19070611 | C19: % | D19: Profit / investment | E19: No
A22: Strategy Takeaways | B22: Strategy Takeaways | C22: Strategy Takeaways | D22: Strategy Takeaways | E22: Strategy Takeaways | F22: Strategy Takeaways | G22: Strategy Takeaways | H22: Strategy Takeaways
A23: Base case: use the weighted DCF + selected trading-comps value as the central target. The model is designed to show how the investment case changes if growth, margins, WACC and terminal growth move. Catalysts include sustained commercial vehicle demand, operating leverage, downstream/service growth, electrification and international expansion. Key risks include cyclicality, commodity costs, geopolitical disruption, execution risk around the proposed IVECO acquisition and valuation de-rating.

Sheet Valuation Dashboard
A1: TATA MOTORS — VALUATION DASHBOARD | B1: TATA MOTORS — VALUATION DASHBOARD | C1: TATA MOTORS — VALUATION DASHBOARD | D1: TATA MOTORS — VALUATION DASHBOARD | E1: TATA MOTORS — VALUATION DASHBOARD | F1: TATA MOTORS — VALUATION DASHBOARD | G1: TATA MOTORS — VALUATION DASHBOARD | H1: TATA MOTORS — VALUATION DASHBOARD | I1: TATA MOTORS — VALUATION DASHBOARD | J1: TATA MOTORS — VALUATION DASHBOARD | K1: TATA MOTORS — VALUATION DASHBOARD | L1: TATA MOTORS — VALUATION DASHBOARD
A3: Decision-support view | FY26A historical base | 7-Sep-2026 market benchmark
A5: Key Valuation Outputs | B5: Key Valuation Outputs | C5: Key Valuation Outputs | D5: Key Valuation Outputs | F5: Valuation Range Visual | G5: Valuation Range Visual | H5: Valuation Range Visual | I5: Valuation Range Visual | J5: Valuation Range Visual | K5: Valuation Range Visual | L5: Valuation Range Visual
A6: Metric | B6: ₹ / Share | C6: ₹ cr | D6: Comment | F6: Method | G6: Current | H6: DCF | I6: Trading Comps | J6: Precedent | K6: Selected Target
A7: Current market price | B7: =Assumptions!$G$8 -> 459.1 | C7: =Assumptions!$G$10 -> 169073 | D7: 7-Sep-2026 | F7: Share Value | G7: =B7 -> 459.1 | H7: =B8 -> 239.508 | I7: =B9 -> 503.58565 | J7: =B10 -> 64.618957 | K7: =B11 -> 371.54682
A8: DCF | B8: =DCF!$B$32 -> 239.508 | C8: =DCF!$B$29 -> 88138.945 | D8: 5-year DCF
A9: Trading Comps | B9: ='Trading Comps'!$C$22 -> 503.58565 | C9: ='Trading Comps'!$B$22 -> 370639.04 | D9: Selected Ashok + Force
A10: Precedent P/S | B10: ='Precedent Transactions'!$B$11*'Historical Financials'!$C$4/Assumptions!$G$9 -> 64.618957 | C10: ='Precedent Transactions'!$B$11*'Historical Financials'!$C$4 -> 23779.776 | D10: Cross-check only
A11: Selected Target | B11: =AVERAGE(B8,B9) -> 371.54682 | C11: =AVERAGE(C8,C9) -> 229388.99 | D11: 50% DCF + 50% Trading Comps
A12: Selected Upside / (Downside) | B12: =B11/B7-1 -> -0.19070611 | D12: vs current price
A15: Investment View | B15: Investment View | C15: Investment View | D15: Investment View
A16: Indicator | B16: Value | C16: Unit | D16: Interpretation
A17: Base-case return | B17: ='Investment Simulation'!$B$19 -> -0.19070611 | C17: % | D17: Selected Target vs current price
A18: Current market cap | B18: =Assumptions!$G$10 -> 169073 | C18: ₹ cr | D18: 7-Sep-2026
A19: FY26 revenue | B19: ='Historical Financials'!$C$4 -> 83855 | C19: ₹ cr | D19: Annual report
A20: FY26 underlying EBITDA | B20: ='Historical Financials'!$C$19 -> 10314 | C20: ₹ cr | D20: Annual report
A21: FY26 free cash flow | B21: ='Historical Financials'!$C$22 -> 12438 | C21: ₹ cr | D21: Annual report
F25: DCF Sensitivity Snapshot | G25: DCF Sensitivity Snapshot | H25: DCF Sensitivity Snapshot | I25: DCF Sensitivity Snapshot | J25: DCF Sensitivity Snapshot | K25: DCF Sensitivity Snapshot | L25: DCF Sensitivity Snapshot
F26: WACC / g | G26: 0.035 | H26: 0.04 | I26: 0.045
F27: 0.1 | G27: =DCF!C38 -> 260.33416 | H27: =DCF!D38 -> 277.37791 | I27: =DCF!E38 -> 297.52054
F28: 0.105 | G28: =DCF!C39 -> 242.58205 | H28: =DCF!D39 -> 256.92836 | I28: =DCF!E39 -> 273.66572
F29: 0.115 | G29: =DCF!C41 -> 214.01365 | H29: =DCF!D41 -> 224.50787 | I29: =DCF!E41 -> 236.50126
F30: 0.12 | G30: =DCF!C42 -> 202.37598 | H30: =DCF!D42 -> 211.47133 | I30: =DCF!E42 -> 221.7794
F32: Recommendation framework: the current price is compared with intrinsic (DCF) and market-based (trading comps) values. The precedent transaction is deliberately not used in the selected target because its structure is not directly comparable.

Sheet Sources
A1: SOURCE REGISTER & DATA LINEAGE | B1: SOURCE REGISTER & DATA LINEAGE | C1: SOURCE REGISTER & DATA LINEAGE | D1: SOURCE REGISTER & DATA LINEAGE | E1: SOURCE REGISTER & DATA LINEAGE | F1: SOURCE REGISTER & DATA LINEAGE
A3: Source ID | B3: Source / Provider | C3: Data Used | D3: As-of / Page | E3: URL / Reference | F3: Workbook Use
A4: TML-AR26-267 | B4: Tata Motors FY26 Integrated Annual Report | C4: Consolidated P&L | D4: p.267 | E4: https://cv.tatamotors.com/annual-reports | F4: Historical FY26A financials
A5: TML-AR26-268-269 | B5: Tata Motors FY26 Integrated Annual Report | C5: Consolidated cash flow | D5: pp.268-269 | E5: https://cv.tatamotors.com/annual-reports | F5: DCF / cash-flow cross-check
A6: TML-AR26-266 | B6: Tata Motors FY26 Integrated Annual Report | C6: Consolidated balance sheet | D6: p.266 | E6: https://cv.tatamotors.com/annual-reports | F6: Net cash / debt bridge
A7: TML-AR26-214 | B7: Tata Motors FY26 Integrated Annual Report | C7: Underlying EBITDA / EBIT | D7: p.214 | E7: https://cv.tatamotors.com/annual-reports | F7: DCF operating base
A8: TML-AR26-117 | B8: Tata Motors FY26 Integrated Annual Report | C8: IVECO purchase consideration / revenue | D8: p.117 | E8: https://cv.tatamotors.com/annual-reports | F8: Precedent transaction cross-check
A9: TML-AR26-220 | B9: Tata Motors FY26 Integrated Annual Report | C9: Liquidity / liquid assets / net cash | D9: p.220 | E9: https://cv.tatamotors.com/annual-reports | F9: Bridge context
A10: MKT-TMCV-20260907 | B10: Business Standard | C10: Tata Motors share price / market cap | D10: 7-Sep-2026 | E10: https://www.business-standard.com/markets/tata-motors-ltd-share-price-93137.html | F10: Current market benchmark
A11: COMP-ASHOK | B11: StockAnalysis | C11: Ashok Leyland FY26 EV/Sales and EV/EBITDA | D11: FY2026 | E11: https://stockanalysis.com/quote/nse/ASHOKLEY/financials/ratios/ | F11: Trading comps
A12: COMP-FORCE | B12: StockAnalysis | C12: Force Motors FY26 EV/Sales and EV/EBITDA | D12: FY2026 | E12: https://stockanalysis.com/quote/nse/FORCEMOT/financials/ratios/ | F12: Trading comps
A13: COMP-EICHER | B13: StockAnalysis | C13: Eicher Motors FY26 EV/Sales and EV/EBITDA | D13: FY2026 | E13: https://stockanalysis.com/quote/nse/EICHERMOT/financials/ratios/ | F13: Reference comp only
... A16: EICHER-FS | B16: StockAnalysis | C16: Eicher Motors FY26 revenue / operating income | D16: FY2026 | E16: https://stockanalysis.com/quote/bom/505200/financials/ | F16: Peer context

Sheet Model Checks
A1: MODEL CHECKS | B1: MODEL CHECKS | C1: MODEL CHECKS | D1: MODEL CHECKS | E1: MODEL CHECKS | F1: MODEL CHECKS
A3: Check | B3: Result | C3: Expected | D3: Status | E3: Source / Logic | F3: Comment
A4: Balance sheet balances | B4: ='Historical Financials'!C32-'Historical Financials'!C32 -> 0 | C4: 0 | D4: =IF(B4=C4,"OK","CHECK") -> OK | E4: Historical Financials | F4: Total assets = equity + liabilities
A5: DCF EV calculation | B5: =DCF!B27-SUM(DCF!B22,DCF!B26) -> 0 | C5: 0 | D5: =IF(ABS(B5-C5)<0.1,"OK","CHECK") -> OK | E5: DCF | F5: EV = PV explicit + PV terminal
A6: DCF equity bridge | B6: =DCF!B29-SUM(DCF!B27,DCF!B28) -> 0 | C6: 0 | D6: =IF(ABS(B6-C6)<0.1,"OK","CHECK") -> OK | E6: DCF | F6: Equity = EV + net cash adjustment
A7: Trading weights | B7: ='Trading Comps'!D22 -> 1 | C7: 1 | D7: =IF(ABS(B7-C7)<0.001,"OK","CHECK") -> OK | E7: Trading Comps | F7: Weights sum to 100%
A8: Shares outstanding | B8: =Assumptions!G9 -> 368 | C8: 368 | D8: =IF(ABS(B8-C8)<0.1,"OK","CHECK") -> OK | E8: Assumptions | F8: Equity share capital ₹736cr / ₹2 face value
A9: Selected target formula | B9: ='Valuation Dashboard'!B11-AVERAGE('Valuation Dashboard'!B8,'Valuation Dashboard'!B9) -> 0 | C9: 0 | D9: =IF(ABS(B9-C9)<0.1,"OK","CHECK") -> OK | E9: Dashboard | F9: Selected target = average DCF & trading comps
